dataanalyser/__init__.py
dataanalyser/duplicates.py
dataanalyser/eda.py
dataanalyser/encoder.py
dataanalyser/explorer.py
dataanalyser/imputer.py
dataanalyser/nullhandler.py
dataanalyser/outlier.py
dataanalyser/plotter.py
dataanalyser/preprocess.py
dataanalyser/statanalysis.py
dataanalyser-0.0.1.dist-info/METADATA
dataanalyser-0.0.1.dist-info/WHEEL
dataanalyser-0.0.1.dist-info/entry_points.txt
dataanalyser-0.0.1.dist-info/top_level.txt
dataanalyser-0.0.1.dist-info/RECORD
