Metadata-Version: 2.1
Name: dataanalyser
Version: 0.0.1
Summary: Automates Exploratory Data Analysis
Home-page: UNKNOWN
Author: Mohamed Anas
Author-email: anasmd890@gmail.com
License: MIT
Platform: UNKNOWN
Classifier: License :: OSI Approved :: MIT License
Classifier: Programming Language :: Python :: 3
Classifier: Programming Language :: Python :: 3.7
Requires-Dist: pandas
Requires-Dist: seaborn
Requires-Dist: numpy
Requires-Dist: scipy
Requires-Dist: matplotlib
Requires-Dist: python-dateutil
Requires-Dist: setuptools
